pyvalhalla.libs/libbrotlicommon-6ce2a53c.so.1.0.6
pyvalhalla.libs/libbrotlidec-811d1be3.so.1.0.6
pyvalhalla.libs/libbsd-526a917f.so.0.12.2
pyvalhalla.libs/libbz2-a1e77c99.so.1.0.6
pyvalhalla.libs/libcom_err-730ca923.so.2.1
pyvalhalla.libs/libcrypt-52aca757.so.1.1.0
pyvalhalla.libs/libcrypto-bdaed0ea.so.1.1.1k
pyvalhalla.libs/libcurl-eaa3cf66.so.4.5.0
pyvalhalla.libs/libczmq-d9886762.so.4.2.1
pyvalhalla.libs/libexpat-d2b8ed35.so.1.6.7
pyvalhalla.libs/libfreexl-25540f57.so.1.2.0
pyvalhalla.libs/libgeos-40815548.so.3.13.1
pyvalhalla.libs/libgeos_c-386b0945.so.1.19.2
pyvalhalla.libs/libgeotiff-cfdb9fd6.so.5.0.0
pyvalhalla.libs/libgssapi_krb5-323bbd21.so.2.2
pyvalhalla.libs/libidn2-2f4a5893.so.0.3.6
pyvalhalla.libs/libjbig-2504a0c3.so.2.1
pyvalhalla.libs/libjpeg-e87d2658.so.62.2.0
pyvalhalla.libs/libk5crypto-9a74ff38.so.3.1
pyvalhalla.libs/libkeyutils-2777d33d.so.1.6
pyvalhalla.libs/libkrb5-a55300e8.so.3.3
pyvalhalla.libs/libkrb5support-e6594cfc.so.0.1
pyvalhalla.libs/liblber-2-d20824ef.4.so.2.10.9
pyvalhalla.libs/libldap-2-cea2a960.4.so.2.10.9
pyvalhalla.libs/libluajit-5-e85ce75d.1.so.2.1.0
pyvalhalla.libs/liblz4-c23f16fe.so.1.8.3
pyvalhalla.libs/liblzma-51a76f52.so.5.2.4
pyvalhalla.libs/libmd-3e096870.so.0.1.0
pyvalhalla.libs/libminizip-89ecf5b6.so.2.8.9
pyvalhalla.libs/libnghttp2-39367a22.so.14.17.0
pyvalhalla.libs/libpcre2-8-516f4c9d.so.0.7.1
pyvalhalla.libs/libpgm-5-d8330baa.2.so.0.0.122
pyvalhalla.libs/libprime_server-d1a42131.so.0.6.7
pyvalhalla.libs/libproj-650ed77a.so.15.3.2
pyvalhalla.libs/libpsl-99becdd3.so.5.3.1
pyvalhalla.libs/librttopo-3fbbac66.so.1.1.0
pyvalhalla.libs/libsasl2-7de4d792.so.3.0.0
pyvalhalla.libs/libselinux-d0805dcb.so.1
pyvalhalla.libs/libsodium-2d1e6a3a.so.23.3.0
pyvalhalla.libs/libspatialite-cf1b7395.so.8.1.0
pyvalhalla.libs/libsqlite3-7a6fdc49.so.3.49.2
pyvalhalla.libs/libssh-05a03e26.so.4.8.7
pyvalhalla.libs/libssl-60250281.so.1.1.1k
pyvalhalla.libs/libtiff-3bdab911.so.5.3.0
pyvalhalla-3.6.1.dist-info/METADATA
pyvalhalla-3.6.1.dist-info/WHEEL
pyvalhalla-3.6.1.dist-info/entry_points.txt
pyvalhalla-3.6.1.dist-info/RECORD
pyvalhalla-3.6.1.dist-info/licenses/COPYING
pyvalhalla-3.6.1.dist-info/sboms/auditwheel.cdx.json
