Metadata-Version: 2.4
Name: pyvalhalla
Version: 3.6.1
Summary: High-level bindings to the Valhalla C++ library
Author: Nils Nolde, Kevin Kreiser
License-Expression: MIT
License-File: COPYING
Project-URL: Homepage, https://github.com/valhalla/valhalla
Project-URL: Documentation, https://valhalla.github.io/valhalla/
Project-URL: Repository, https://github.com/valhalla/valhalla
Project-URL: Issues, https://github.com/valhalla/valhalla/issues
Project-URL: Changelog, https://github.com/valhalla/valhalla/blob/master/CHANGELOG.md
Requires-Python: >=3.9.0
